better_setuptools_git_version.py
better_setuptools_git_version-1.0.4.dist-info/LICENSE
better_setuptools_git_version-1.0.4.dist-info/METADATA
better_setuptools_git_version-1.0.4.dist-info/WHEEL
better_setuptools_git_version-1.0.4.dist-info/entry_points.txt
better_setuptools_git_version-1.0.4.dist-info/top_level.txt
better_setuptools_git_version-1.0.4.dist-info/RECORD
