Metadata-Version: 2.1
Name: better-setuptools-git-version
Version: 1.0.4
Summary: Automatically set package version using git tags.
Home-page: https://github.com/vivin/better-setuptools-git-version
Author: Vivin Paliath
Author-email: vivin.paliath@gmail.com
License: MIT
Keywords: setuptools git version-control
Platform: UNKNOWN
Classifier: Framework :: Setuptools Plugin
Classifier: Intended Audience :: Developers
Classifier: License :: OSI Approved :: MIT License
Classifier: Programming Language :: Python :: 2
Classifier: Programming Language :: Python :: 3
Classifier: Development Status :: 5 - Production/Stable
Requires-Dist: setuptools (>=8.0)
